LICENSE
MANIFEST.in
README.rst
setup.py
confutil/__init__.py
confutil/config.py
confutil.egg-info/PKG-INFO
confutil.egg-info/SOURCES.txt
confutil.egg-info/dependency_links.txt
confutil.egg-info/entry_points.txt
confutil.egg-info/requires.txt
confutil.egg-info/top_level.txt
confutil/.ropeproject/config.py