Metadata-Version: 1.1
Name: confutil
Version: 0.1.3
Summary: Configuration utility to ease navigation of local and system configurations
Home-page: https://bitbucket.org/johannestaas/confutil
Author: Johan Nestaas
Author-email: johannestaas@gmail.com
License: GPLv3+
Platform: UNKNOWN
Classifier: Development Status :: 4 - Beta
Classifier: License :: OSI Approved :: GNU General Public License v3 or later (GPLv3+)
Classifier: Environment :: Console
Classifier: Environment :: X11 Applications :: Qt
Classifier: Environment :: MacOS X
Classifier: Environment :: Win32 (MS Windows)
Classifier: Operating System :: POSIX
Classifier: Operating System :: MacOS :: MacOS X
Classifier: Operating System :: Microsoft :: Windows
Classifier: Programming Language :: Python
